<?xml version="1.0" encoding="UTF-8"?>
<ruhm>
    <opilane>
        <nimi>Gleb</nimi>
        <perekonnanimi>Sotsjov</perekonnanimi>
        <sugu>mees</sugu>
        <koduleht>GlebSotsjov23.thkit.ee</koduleht>
        <juuksevarv>kastani</juuksevarv>
    </opilane>

    <opilane>
        <nimi>Valeria</nimi>
        <perekonnanimi>Allik</perekonnanimi>
        <sugu>naine</sugu>
        <koduleht>ValeriaAllik23.thkit.ee</koduleht>
        <juuksevarv>kastani</juuksevarv>
    </opilane>

    <opilane>
        <nimi>Martin</nimi>
        <perekonnanimi>Sild</perekonnanimi>
        <sugu>mees</sugu>
        <koduleht>KirillSats23.thkit.ee</koduleht>
        <juuksevarv>tuumepruun</juuksevarv>
    </opilane>

    <opilane>
        <nimi>David L</nimi>
        <perekonnanimi>Lennuk</perekonnanimi>
        <sugu>mees</sugu>
        <koduleht>DavidLennuk23.thkit.ee</koduleht>
        <juuksevarv>helepruun</juuksevarv>
    </opilane>

    <opilane>
        <nimi>Marija</nimi>
        <perekonnanimi>Gorbunova</perekonnanimi>
        <sugu>naine</sugu>
        <koduleht>MarijaGorbunova23.thkit.ee</koduleht>
        <juuksevarv>heelepruun</juuksevarv>
    </opilane>

    <opilane>
        <nimi>Roman</nimi>
        <perekonnanimi>Sandakov</perekonnanimi>
        <sugu>mees</sugu>
        <koduleht>RomanSandakov23.thkit.ee</koduleht>
        <juuksevarv>tuumepruun</juuksevarv>
    </opilane>

    <opilane>
        <nimi>Aleksandra</nimi>
        <perekonnanimi>Semjonova</perekonnanimi>
        <sugu>naine</sugu>
        <koduleht>AleksandraSemjonova23.thkit.ee</koduleht>
        <juuksevarv>kastani</juuksevarv>
    </opilane>

    <opilane>
        <nimi>Vsevolod</nimi>
        <perekonnanimi>Tsarev</perekonnanimi>
        <sugu>mees</sugu>
        <koduleht>VsevolodTsarev23.thkit.ee</koduleht>
        <juuksevarv>pruun</juuksevarv>
    </opilane>

    <opilane>
        <nimi>Daria</nimi>
        <perekonnanimi>Halchenko</perekonnanimi>
        <sugu>naine</sugu>
        <koduleht>DariaHalchenko23.thkit.ee</koduleht>
        <juuksevarv>punane</juuksevarv>
    </opilane>

    <opilane>
        <nimi>Bogdan</nimi>
        <perekonnanimi>Viblyy</perekonnanimi>
        <sugu>mees</sugu>
        <koduleht>BogdanViblyy23.thkit.ee</koduleht>
        <juuksevarv>kastani</juuksevarv>
    </opilane>

    <opilane>
        <nimi>Jelizaveta</nimi>
        <perekonnanimi>Ostapjuk</perekonnanimi>
        <sugu>naine</sugu>
        <koduleht>JelizavetaOstapjuk23.thkit.ee</koduleht>
        <juuksevarv>heelepruun</juuksevarv>
    </opilane>

    <opilane>
        <nimi>Anton</nimi>
        <perekonnanimi>Ivanov</perekonnanimi>
        <sugu>mees</sugu>
        <koduleht>AntonIvanov23.thkit.ee</koduleht>
        <juuksevarv>kastani</juuksevarv>
    </opilane>

    <opilane>
        <nimi>Timur</nimi>
        <perekonnanimi>Basirov</perekonnanimi>
        <sugu>mees</sugu>
        <koduleht>TimurBasirov23.thkit.ee</koduleht>
        <juuksevarv>pruun</juuksevarv>
    </opilane>

    <opilane>
        <nimi>Erik</nimi>
        <perekonnanimi>Gerega</perekonnanimi>
        <sugu>mees</sugu>
        <koduleht>ErikGerega23.thkit.ee</koduleht>
        <juuksevarv>kastani</juuksevarv>
    </opilane>

    <opilane>
        <nimi>Vladislav</nimi>
        <perekonnanimi>Kudriashev</perekonnanimi>
        <sugu>mees</sugu>
        <koduleht>VladislavKudriashev23.thkit.ee</koduleht>
        <juuksevarv>heelepruun</juuksevarv>
    </opilane>

    <opilane>
        <nimi>Aleksander</nimi>
        <perekonnanimi>Milisenko</perekonnanimi>
        <sugu>mees</sugu>
        <koduleht>AleksanderMilisenko23.thkit.ee</koduleht>
        <juuksevarv>blond</juuksevarv>
    </opilane>

    <opilane>
        <nimi>David M</nimi>
        <perekonnanimi>Myrseth</perekonnanimi>
        <sugu>mees</sugu>
        <koduleht>DavidMyrseth23.thkit.ee</koduleht>
        <juuksevarv>heelepruun</juuksevarv>
    </opilane>

    <opilane>
        <nimi>Bogdan</nimi>
        <perekonnanimi>Sergachev</perekonnanimi>
        <sugu>mees</sugu>
        <koduleht>BogdanSergachev23.thkit.ee</koduleht>
        <juuksevarv>punane</juuksevarv>
    </opilane>


    <opilane>
        <nimi>Aleksandr</nimi>
        <perekonnanimi>Nadvornoi</perekonnanimi>
        <sugu>mees</sugu>
        <koduleht>AleksandrNadvornoi23.thkit.ee</koduleht>
        <juuksevarv>tuumepruun</juuksevarv>
    </opilane>
    
        <opilane><nimi>Dima</nimi><koduleht>GlebSotsjov23.thkit.ee</koduleht><sugu>mees</sugu><juuksevarv>sinine</juuksevarv></opilane> </ruhm>
